{
  "document": {
    "document_id": "0aeaa6091659af4418b724141a8e520407c41f76fda7a6f6304674701cb08ba4",
    "source_path": "/Users/pranesh/Devloper/Cloud Product/Doc/data/uploads/7294dc7f09524164b02649af30c6ef89_Diabetes Screening Profile - 44863.pdf",
    "file_name": "7294dc7f09524164b02649af30c6ef89_Diabetes Screening Profile - 44863.pdf",
    "document_type": "pdf",
    "text": "Glucose Tolerance Test - (GTT 2 specimens) after 75gm\nHexokinase\nGlucose (Fasting) 89 mg/dL 74 - 99\nBlood Glucose After 2 hr 75 mg/dl 100 - 139\nComment\nImpaired Fasting Glucose:\nFasting P. Glucose 100 - 125\nP.Glucose after 2 hrs 100 - 139\nImpaired Glucose Tolerance:\nFasting P.Glucose 74 - 99\nP.Glucose after 2 hrs 140 - 199\nDiabetes:\nFasting P.Glucose \u0095\u0003\u0014\u0015\u0019\nP.Glucose after 2 hrs \u0095\u0003\u0015\u0013\u0013\nDiagnosis of Diabetes mellitus (DM), impaired glucose tolerance (IGT), impaired fasting glucose (IFG) on first occasion should be confirmed on another day.\n3DWLHQWV\u0003ZLWK\u0003,)*\u0003DQG\u0012RU\u0003,*7\u0003DUH\u0003UHIHUUHG\u0003WR\u0003DV\u0003KDYLQJ\u0003\u00b3SUH\u0003GLDEHWHV\u00b4\u0003EHFDXVH\u0003RI\u0003WKHLU\u0003KLJK\u0003ULVN\u0003RI\u0003GHYHORSLQJ\u0003WKH\u0003GLDEHWHV\u0003LQ\u0003WKH\u0003IXWXUH\u0011\u00037KHVH\u0003SDWLHQWV\u0003DUH\u0003DOVR\u0003DW\nhigh risk for cardiovascular disease.\nLaboratory Investigation Report\nPatient Name : Mrs. Abhirupa Sen\nAge/Gender : 34 Y 0 M 0 D /F\nMax ID/Mobile : ML01514672/9879765568\nLab ID : 1887102100063\nRef Doctor : Dr.Jayshree Sundar\nPassport No. :\nCentre : 2132 - Azmat Diagnostics\nOP/IP No : /\nCollection Date/Time : 24/Oct/2021 12:27PM\nReceiving Date : 24/Oct/2021\nReporting Date : 24/Oct/2021\nClinical Biochemistry\nDiabetes Screening Profile\nTest Name Result Unit Bio Ref Interval\n6,1\u00031R\n%\u0015E\u0014\u0013\u0018\u001b\u0018\u0019\u0017\u000f\u0003\u00037HVW\u00033HUIRUPHG\u0003DW\u0003\n\n\u0014\u0013\u0003\u0010\u00030D[\u0003+RVSLWDO\u0003\u0010\u00036DNHW\u00030\u00036\u00036\u0003+\u000f\u00033UHVV\u0003(QFODYH\u00035RDG\u000f\u00030DQGLU\u00030DUJ\u000f\u00036DNHW\u000f\u00031HZ\u0003'HOKL\u000f\u0003'HOKL\u0003\u0014\u0014\u0013\u0013\u0014\u001a\n%RRNLQJ\u0003&HQWUH\u0003\n\u0015\u0014\u0016\u0015\u0003\u0010\u0003$]PDW\u0003'LDJQRVWLFV\u000f\u0003'\u0010\u0014\u0018\u0003)RXUWK\u0003)ORRU\u000f\u0003+D]L\u0003&RORQ\\\u000f\u0003-DPLD\u00031DJDU\u000f\u00032NKOD\u0003\u000f\u00031HZ\u0003'HOKL\u0010\u0015\u0018\u000f\u0003\n\u001b\u001a\u0016\u0019\u0013\u0019\u0014\u001a\u0016\n7KH\u0003DXWKHQWLFLW\\\u0003RI\u0003WKH\u0003UHSRUW\u0003FDQ\u0003EH\u0003YHULILHG\u0003E\\\u0003VFDQQLQJ\u0003WKH\u00034\u00035\u0003&RGH\u0003RQ\u0003WRS\u0003RI\u0003WKH\u0003SDJH\nPage 1 of 3\n\nGlycosylated Haemoglobin (HbA1C),EDTA Routine\nHPLC\nDate 24/Oct/2021\n12:27PM\nUnit Bio Ref Interval\nGlycosylated\nHaemoglobin(Hb A1c)\n4.7 % < 5.7\nGlycosylated\nHaemoglobin(Hb A1c)\nIFCC\n27.85 mmol/mol < 39.0\nAverage Glucose Value\nFor the Last 3 Months\n88.19 mg/dL\nAverage Glucose Value\nFor the Last 3 Months\nIFCC\n4.88 mmol/L\nInterpretation The following HbA1c ranges recommended by the American Diabetes Assocation(ADA) may be used as an aid in the diagnosis of diabetes\nmellitus.\nHbA1C(NGSP %) HbA1C(IFCC mmol/mol) Suggested Diagnosis\n> 6.5 > 48 Diabetic\n5.7 - 6.4 39 - 47 Pre- Diabetic\n< 5.7 < 39 Non - Diabetic\nHbA1C provides a useful index of average glycaemia over the preceding 6-8 weeks.\nIt is suggested that HbA1c is measured every 6 months in stable patients, every 3 months in patients with unstable metabolic control and every month in pregnancy.\nIncreased Glycated hemoglobin is a reflection of Hyperglycemia.\nKindly correlate with clinical findings\n*** End Of Report ***\nLaboratory Investigation Report\nPatient Name : Mrs. Abhirupa Sen\nAge/Gender : 34 Y 0 M 0 D /F\nMax ID/Mobile : ML01514672/9879765568\nLab ID : 1887102100063\nRef Doctor : Dr.Jayshree Sundar\nPassport No. :\nCentre : 2132 - Azmat Diagnostics\nOP/IP No : /\nCollection Date/Time : 24/Oct/2021 12:27PM\nReceiving Date : 24/Oct/2021\nReporting Date : 24/Oct/2021\nClinical Biochemistry\nDiabetes Screening Profile\n6,1\u00031R\n%\u0015E\u0014\u0013\u0018\u001b\u0018\u0019\u0017\u000f\u0003\u00037HVW\u00033HUIRUPHG\u0003DW\u0003\n\n\u0014\u0013\u0003\u0010\u00030D[\u0003+RVSLWDO\u0003\u0010\u00036DNHW\u00030\u00036\u00036\u0003+\u000f\u00033UHVV\u0003(QFODYH\u00035RDG\u000f\u00030DQGLU\u00030DUJ\u000f\u00036DNHW\u000f\u00031HZ\u0003'HOKL\u000f\u0003'HOKL\u0003\u0014\u0014\u0013\u0013\u0014\u001a\n%RRNLQJ\u0003&HQWUH\u0003\n\u0015\u0014\u0016\u0015\u0003\u0010\u0003$]PDW\u0003'LDJQRVWLFV\u000f\u0003'\u0010\u0014\u0018\u0003)RXUWK\u0003)ORRU\u000f\u0003+D]L\u0003&RORQ\\\u000f\u0003-DPLD\u00031DJDU\u000f\u00032NKOD\u0003\u000f\u00031HZ\u0003'HOKL\u0010\u0015\u0018\u000f\u0003\n\u001b\u001a\u0016\u0019\u0013\u0019\u0014\u001a\u0016\n7KH\u0003DXWKHQWLFLW\\\u0003RI\u0003WKH\u0003UHSRUW\u0003FDQ\u0003EH\u0003YHULILHG\u0003E\\\u0003VFDQQLQJ\u0003WKH\u00034\u00035\u0003&RGH\u0003RQ\u0003WRS\u0003RI\u0003WKH\u0003SDJH\nPage 2 of 3\n\nLaboratory Investigation Report\nPatient Name : Mrs. Abhirupa Sen\nAge/Gender : 34 Y 0 M 0 D /F\nMax ID/Mobile : ML01514672/9879765568\nLab ID : 1887102100063\nRef Doctor : Dr.Jayshree Sundar\nPassport No. :\nCentre : 2132 - Azmat Diagnostics\nOP/IP No : /\nCollection Date/Time : 24/Oct/2021 12:27PM\nReceiving Date : 24/Oct/2021\nReporting Date : 24/Oct/2021\nClinical Biochemistry\nDiabetes Screening Profile\n6,1\u00031R\n%\u0015E\u0014\u0013\u0018\u001b\u0018\u0019\u0017\u000f\u0003\u00037HVW\u00033HUIRUPHG\u0003DW\u0003\n\n\u0014\u0013\u0003\u0010\u00030D[\u0003+RVSLWDO\u0003\u0010\u00036DNHW\u00030\u00036\u00036\u0003+\u000f\u00033UHVV\u0003(QFODYH\u00035RDG\u000f\u00030DQGLU\u00030DUJ\u000f\u00036DNHW\u000f\u00031HZ\u0003'HOKL\u000f\u0003'HOKL\u0003\u0014\u0014\u0013\u0013\u0014\u001a\n%RRNLQJ\u0003&HQWUH\u0003\n\u0015\u0014\u0016\u0015\u0003\u0010\u0003$]PDW\u0003'LDJQRVWLFV\u000f\u0003'\u0010\u0014\u0018\u0003)RXUWK\u0003)ORRU\u000f\u0003+D]L\u0003&RORQ\\\u000f\u0003-DPLD\u00031DJDU\u000f\u00032NKOD\u0003\u000f\u00031HZ\u0003'HOKL\u0010\u0015\u0018\u000f\u0003\n\u001b\u001a\u0016\u0019\u0013\u0019\u0014\u001a\u0016\n7KH\u0003DXWKHQWLFLW\\\u0003RI\u0003WKH\u0003UHSRUW\u0003FDQ\u0003EH\u0003YHULILHG\u0003E\\\u0003VFDQQLQJ\u0003WKH\u00034\u00035\u0003&RGH\u0003RQ\u0003WRS\u0003RI\u0003WKH\u0003SDJH\nPage 3 of 3",
    "metadata": {
      "page_count": 3,
      "pages_with_text": 3,
      "pages_processed": 3,
      "file_size_bytes": 357601
    }
  },
  "cleaned_document": {
    "document_id": "0aeaa6091659af4418b724141a8e520407c41f76fda7a6f6304674701cb08ba4",
    "cleaned_text": "Glucose Tolerance Test - (GTT 2 specimens) after 75gm Hexokinase Glucose (Fasting) 89 mg/dL 74 - 99 Blood Glucose After 2 hr 75 mg/dl 100 - 139 Comment Impaired Fasting Glucose: Fasting P. Glucose 100 - 125 P.Glucose after 2 hrs 100 - 139 Impaired Glucose Tolerance: Fasting P.Glucose 74 - 99 P.Glucose after 2 hrs 140 - 199 Diabetes: Fasting P.Glucose \u0095\u0003\u0014\u0015\u0019 P.Glucose after 2 hrs \u0095\u0003\u0015\u0013\u0013 Diagnosis of Diabetes mellitus (DM), impaired glucose tolerance (IGT), impaired fasting glucose (IFG) on first occasion should be confirmed on another day. 3DWLHQWV\u0003ZLWK\u0003,)*\u0003DQG\u0012RU\u0003,*7\u0003DUH\u0003UHIHUUHG\u0003WR\u0003DV\u0003KDYLQJ\u0003\u00b3SUH\u0003GLDEHWHV\u00b4\u0003EHFDXVH\u0003RI\u0003WKHLU\u0003KLJK\u0003ULVN\u0003RI\u0003GHYHORSLQJ\u0003WKH\u0003GLDEHWHV\u0003LQ\u0003WKH\u0003IXWXUH\u0011\u00037KHVH\u0003SDWLHQWV\u0003DUH\u0003DOVR\u0003DW high risk for cardiovascular disease. Laboratory Investigation Report Patient Name : Mrs. Abhirupa Sen Age/Gender : 34 Y 0 M 0 D /F Max ID/Mobile : ML01514672/9879765568 Lab ID : 1887102100063 Ref Doctor : Dr.Jayshree Sundar Passport No. : Centre : 2132 - Azmat Diagnostics OP/IP No : / Collection Date/Time : 24/Oct/2021 12:27PM Receiving Date : 24/Oct/2021 Reporting Date : 24/Oct/2021 Clinical Biochemistry Diabetes Screening Profile Test Name Result Unit Bio Ref Interval 6,1\u00031R %\u0015E\u0014\u0013\u0018\u001b\u0018\u0019\u0017\u000f\u0003\u00037HVW\u00033HUIRUPHG\u0003DW\u0003\n\n\u0014\u0013\u0003\u0010\u00030D[\u0003+RVSLWDO\u0003\u0010\u00036DNHW\u00030\u00036\u00036\u0003+\u000f\u00033UHVV\u0003(QFODYH\u00035RDG\u000f\u00030DQGLU\u00030DUJ\u000f\u00036DNHW\u000f\u00031HZ\u0003'HOKL\u000f\u0003'HOKL\u0003\u0014\u0014\u0013\u0013\u0014\u001a %RRNLQJ\u0003&HQWUH\u0003 \u0015\u0014\u0016\u0015\u0003\u0010\u0003$]PDW\u0003'LDJQRVWLFV\u000f\u0003'\u0010\u0014\u0018\u0003)RXUWK\u0003)ORRU\u000f\u0003+D]L\u0003&RORQ\\\u000f\u0003-DPLD\u00031DJDU\u000f\u00032NKOD\u0003\u000f\u00031HZ\u0003'HOKL\u0010\u0015\u0018\u000f\u0003 \u001b\u001a\u0016\u0019\u0013\u0019\u0014\u001a\u0016 7KH\u0003DXWKHQWLFLW\\\u0003RI\u0003WKH\u0003UHSRUW\u0003FDQ\u0003EH\u0003YHULILHG\u0003E\\\u0003VFDQQLQJ\u0003WKH\u00034\u00035\u0003&RGH\u0003RQ\u0003WRS\u0003RI\u0003WKH\u0003SDJH\n\nGlycosylated Haemoglobin (HbA1C),EDTA Routine HPLC Date 24/Oct/2021 12:27PM Unit Bio Ref Interval Glycosylated Haemoglobin(Hb A1c) 4.7 % < 5.7 Glycosylated Haemoglobin(Hb A1c) IFCC 27.85 mmol/mol < 39.0 Average Glucose Value For the Last 3 Months 88.19 mg/dL Average Glucose Value For the Last 3 Months IFCC 4.88 mmol/L Interpretation The following HbA1c ranges recommended by the American Diabetes Assocation(ADA) may be used as an aid in the diagnosis of diabetes mellitus. HbA1C(NGSP %) HbA1C(IFCC mmol/mol) Suggested Diagnosis > 6.5 > 48 Diabetic 5.7 - 6.4 39 - 47 Pre- Diabetic < 5.7 < 39 Non - Diabetic HbA1C provides a useful index of average glycaemia over the preceding 6-8 weeks. It is suggested that HbA1c is measured every 6 months in stable patients, every 3 months in patients with unstable metabolic control and every month in pregnancy. Increased Glycated hemoglobin is a reflection of Hyperglycemia. Kindly correlate with clinical findings *** End Of Report *** Laboratory Investigation Report Patient Name : Mrs. Abhirupa Sen Age/Gender : 34 Y 0 M 0 D /F Max ID/Mobile : ML01514672/9879765568 Lab ID : 1887102100063 Ref Doctor : Dr.Jayshree Sundar Passport No. : Centre : 2132 - Azmat Diagnostics OP/IP No : / Collection Date/Time : 24/Oct/2021 12:27PM Receiving Date : 24/Oct/2021 Reporting Date : 24/Oct/2021 Clinical Biochemistry Diabetes Screening Profile 6,1\u00031R %\u0015E\u0014\u0013\u0018\u001b\u0018\u0019\u0017\u000f\u0003\u00037HVW\u00033HUIRUPHG\u0003DW\u0003\n\n\u0014\u0013\u0003\u0010\u00030D[\u0003+RVSLWDO\u0003\u0010\u00036DNHW\u00030\u00036\u00036\u0003+\u000f\u00033UHVV\u0003(QFODYH\u00035RDG\u000f\u00030DQGLU\u00030DUJ\u000f\u00036DNHW\u000f\u00031HZ\u0003'HOKL\u000f\u0003'HOKL\u0003\u0014\u0014\u0013\u0013\u0014\u001a %RRNLQJ\u0003&HQWUH\u0003 \u0015\u0014\u0016\u0015\u0003\u0010\u0003$]PDW\u0003'LDJQRVWLFV\u000f\u0003'\u0010\u0014\u0018\u0003)RXUWK\u0003)ORRU\u000f\u0003+D]L\u0003&RORQ\\\u000f\u0003-DPLD\u00031DJDU\u000f\u00032NKOD\u0003\u000f\u00031HZ\u0003'HOKL\u0010\u0015\u0018\u000f\u0003 \u001b\u001a\u0016\u0019\u0013\u0019\u0014\u001a\u0016 7KH\u0003DXWKHQWLFLW\\\u0003RI\u0003WKH\u0003UHSRUW\u0003FDQ\u0003EH\u0003YHULILHG\u0003E\\\u0003VFDQQLQJ\u0003WKH\u00034\u00035\u0003&RGH\u0003RQ\u0003WRS\u0003RI\u0003WKH\u0003SDJH\n\nLaboratory Investigation Report Patient Name : Mrs. Abhirupa Sen Age/Gender : 34 Y 0 M 0 D /F Max ID/Mobile : ML01514672/9879765568 Lab ID : 1887102100063 Ref Doctor : Dr.Jayshree Sundar Passport No. : Centre : 2132 - Azmat Diagnostics OP/IP No : / Collection Date/Time : 24/Oct/2021 12:27PM Receiving Date : 24/Oct/2021 Reporting Date : 24/Oct/2021 Clinical Biochemistry Diabetes Screening Profile 6,1\u00031R %\u0015E\u0014\u0013\u0018\u001b\u0018\u0019\u0017\u000f\u0003\u00037HVW\u00033HUIRUPHG\u0003DW\u0003\n\n\u0014\u0013\u0003\u0010\u00030D[\u0003+RVSLWDO\u0003\u0010\u00036DNHW\u00030\u00036\u00036\u0003+\u000f\u00033UHVV\u0003(QFODYH\u00035RDG\u000f\u00030DQGLU\u00030DUJ\u000f\u00036DNHW\u000f\u00031HZ\u0003'HOKL\u000f\u0003'HOKL\u0003\u0014\u0014\u0013\u0013\u0014\u001a %RRNLQJ\u0003&HQWUH\u0003 \u0015\u0014\u0016\u0015\u0003\u0010\u0003$]PDW\u0003'LDJQRVWLFV\u000f\u0003'\u0010\u0014\u0018\u0003)RXUWK\u0003)ORRU\u000f\u0003+D]L\u0003&RORQ\\\u000f\u0003-DPLD\u00031DJDU\u000f\u00032NKOD\u0003\u000f\u00031HZ\u0003'HOKL\u0010\u0015\u0018\u000f\u0003 \u001b\u001a\u0016\u0019\u0013\u0019\u0014\u001a\u0016 7KH\u0003DXWKHQWLFLW\\\u0003RI\u0003WKH\u0003UHSRUW\u0003FDQ\u0003EH\u0003YHULILHG\u0003E\\\u0003VFDQQLQJ\u0003WKH\u00034\u00035\u0003&RGH\u0003RQ\u0003WRS\u0003RI\u0003WKH\u0003SDJH",
    "metadata": {
      "page_count": 3,
      "pages_with_text": 3,
      "pages_processed": 3,
      "file_size_bytes": 357601,
      "storage_location": "/Users/pranesh/Devloper/Cloud Product/Doc/data/uploads/7294dc7f09524164b02649af30c6ef89_Diabetes Screening Profile - 44863.pdf",
      "storage_backend": "local",
      "original_char_count": 4049,
      "cleaned_char_count": 4013,
      "paragraph_count": 6
    }
  },
  "chunking": {
    "document_id": "0aeaa6091659af4418b724141a8e520407c41f76fda7a6f6304674701cb08ba4",
    "chunks": [
      {
        "chunk_id": "a159b7591b450e49c4ed39cb4057bf2d8379fb730d676e6a7ce35b24cd766f3d",
        "document_id": "0aeaa6091659af4418b724141a8e520407c41f76fda7a6f6304674701cb08ba4",
        "chunk_index": 0,
        "text": "Glucose Tolerance Test - (GTT 2 specimens) after 75gm Hexokinase Glucose (Fasting) 89 mg/dL 74 - 99 Blood Glucose After 2 hr 75 mg/dl 100 - 139 Comment Impaired Fasting Glucose: Fasting P. Glucose 100 - 125 P.Glucose after 2 hrs 100 - 139 Impaired Glucose Tolerance: Fasting P.Glucose 74 - 99 P.Glucose after 2 hrs 140 - 199 Diabetes: Fasting P.Glucose \u0095\u0003\u0014\u0015\u0019 P.Glucose after 2 hrs \u0095\u0003\u0015\u0013\u0013 Diagnosis of Diabetes mellitus (DM), impaired glucose tolerance (IGT), impaired fasting glucose (IFG) on first occasion should be confirmed on another day. 3DWLHQWV\u0003ZLWK\u0003,)*\u0003DQG\u0012RU\u0003,*7\u0003DUH\u0003UHIHUUHG\u0003WR\u0003DV\u0003KDYLQJ\u0003\u00b3SUH\u0003GLDEHWHV\u00b4\u0003EHFDXVH\u0003RI\u0003WKHLU\u0003KLJK\u0003ULVN\u0003RI\u0003GHYHORSLQJ\u0003WKH\u0003GLDEHWHV\u0003LQ\u0003WKH\u0003IXWXUH\u0011\u00037KHVH\u0003SDWLHQWV\u0003DUH\u0003DOVR\u0003DW high risk for cardiovascular disease. Laboratory Investigation Report Patient Name : Mrs. Abhirupa Sen Age/Gender : 34 Y 0 M 0 D /F Max ID/Mobile : ML01514672/9879765568 Lab ID : 1887102100063 Ref Doctor : Dr.Jayshree Sundar Passport No. : Centre : 2132 - Azmat Diagnostics OP/IP No : / Collection Date/Time : 24/Oct/2021 12:27PM Receiving Date : 24/Oct/2021 Reporting Date : 24/Oct/2021 Clinical Biochemistry Diabetes Screening Profile Test Name Result Unit Bio Ref Interval 6,1\u00031R %\u0015E\u0014\u0013\u0018\u001b\u0018\u0019\u0017\u000f\u0003\u00037HVW\u00033HUIRUPHG\u0003DW\u0003\n\n\u0014\u0013\u0003\u0010\u00030D[\u0003+RVSLWDO\u0003\u0010\u00036DNHW\u00030\u00036\u00036\u0003+\u000f\u00033UHVV\u0003(QFODYH\u00035RDG\u000f\u00030DQGLU\u00030DUJ\u000f\u00036DNHW\u000f\u00031HZ\u0003'HOKL\u000f\u0003'HOKL\u0003\u0014\u0014\u0013\u0013\u0014\u001a %RRNLQJ\u0003&HQWUH\u0003 \u0015\u0014\u0016\u0015\u0003\u0010\u0003$]PDW\u0003'LDJQRVWLFV\u000f\u0003'\u0010\u0014\u0018\u0003)RXUWK\u0003)ORRU\u000f\u0003+D]L\u0003&RORQ\\\u000f\u0003-DPLD\u00031DJDU\u000f\u00032NKOD\u0003\u000f\u00031HZ\u0003'HOKL\u0010\u0015\u0018\u000f\u0003 \u001b\u001a\u0016\u0019\u0013\u0019\u0014\u001a\u0016 7KH\u0003DXWKHQWLFLW\\\u0003RI\u0003WKH\u0003UHSRUW\u0003FDQ\u0003EH\u0003YHULILHG\u0003E\\\u0003VFDQQLQJ\u0003WKH\u00034\u00035\u0003&RGH\u0003RQ\u0003WRS\u0003RI\u0003WKH\u0003SDJH\n\nGlycosylated Haemoglobin (HbA1C),EDTA Routine HPLC Date 24/Oct/2021 12:27PM Unit Bio Ref Interval Glycosylated Haemoglobin(Hb A1c) 4.7 % < 5.7 Glycosylated Haemoglobin(Hb A1c) IFCC 27.85 mmol/mol < 39.0 Average Glucose Value For the Last 3 Months 88.19 mg/dL Average Glucose Value For the Last 3 Months IFCC 4.88 mmol/L Interpretation The following HbA1c ranges recommended by the American Diabetes Assocation(ADA) may be used as an aid in the diagnosis of diabetes mellitus. HbA1C(NGSP %) HbA1C(IFCC mmol/mol) Suggested Diagnosis >",
        "start_char": 0,
        "end_char": 2068,
        "token_count": 250,
        "metadata": {
          "page_count": 3,
          "pages_with_text": 3,
          "pages_processed": 3,
          "file_size_bytes": 357601,
          "storage_location": "/Users/pranesh/Devloper/Cloud Product/Doc/data/uploads/7294dc7f09524164b02649af30c6ef89_Diabetes Screening Profile - 44863.pdf",
          "storage_backend": "local",
          "original_char_count": 4049,
          "cleaned_char_count": 4013,
          "paragraph_count": 6,
          "start_token_index": 0,
          "end_token_index": 249
        }
      },
      {
        "chunk_id": "1a418284e502793c512b5bd8ea9a15c7feb91cd8d9593b0aa46d35eb4782b4e4",
        "document_id": "0aeaa6091659af4418b724141a8e520407c41f76fda7a6f6304674701cb08ba4",
        "chunk_index": 1,
        "text": "Glucose Value For the Last 3 Months IFCC 4.88 mmol/L Interpretation The following HbA1c ranges recommended by the American Diabetes Assocation(ADA) may be used as an aid in the diagnosis of diabetes mellitus. HbA1C(NGSP %) HbA1C(IFCC mmol/mol) Suggested Diagnosis > 6.5 > 48 Diabetic 5.7 - 6.4 39 - 47 Pre- Diabetic < 5.7 < 39 Non - Diabetic HbA1C provides a useful index of average glycaemia over the preceding 6-8 weeks. It is suggested that HbA1c is measured every 6 months in stable patients, every 3 months in patients with unstable metabolic control and every month in pregnancy. Increased Glycated hemoglobin is a reflection of Hyperglycemia. Kindly correlate with clinical findings *** End Of Report *** Laboratory Investigation Report Patient Name : Mrs. Abhirupa Sen Age/Gender : 34 Y 0 M 0 D /F Max ID/Mobile : ML01514672/9879765568 Lab ID : 1887102100063 Ref Doctor : Dr.Jayshree Sundar Passport No. : Centre : 2132 - Azmat Diagnostics OP/IP No : / Collection Date/Time : 24/Oct/2021 12:27PM Receiving Date : 24/Oct/2021 Reporting Date : 24/Oct/2021 Clinical Biochemistry Diabetes Screening Profile 6,1\u00031R %\u0015E\u0014\u0013\u0018\u001b\u0018\u0019\u0017\u000f\u0003\u00037HVW\u00033HUIRUPHG\u0003DW\u0003\n\n\u0014\u0013\u0003\u0010\u00030D[\u0003+RVSLWDO\u0003\u0010\u00036DNHW\u00030\u00036\u00036\u0003+\u000f\u00033UHVV\u0003(QFODYH\u00035RDG\u000f\u00030DQGLU\u00030DUJ\u000f\u00036DNHW\u000f\u00031HZ\u0003'HOKL\u000f\u0003'HOKL\u0003\u0014\u0014\u0013\u0013\u0014\u001a %RRNLQJ\u0003&HQWUH\u0003 \u0015\u0014\u0016\u0015\u0003\u0010\u0003$]PDW\u0003'LDJQRVWLFV\u000f\u0003'\u0010\u0014\u0018\u0003)RXUWK\u0003)ORRU\u000f\u0003+D]L\u0003&RORQ\\\u000f\u0003-DPLD\u00031DJDU\u000f\u00032NKOD\u0003\u000f\u00031HZ\u0003'HOKL\u0010\u0015\u0018\u000f\u0003 \u001b\u001a\u0016\u0019\u0013\u0019\u0014\u001a\u0016 7KH\u0003DXWKHQWLFLW\\\u0003RI\u0003WKH\u0003UHSRUW\u0003FDQ\u0003EH\u0003YHULILHG\u0003E\\\u0003VFDQQLQJ\u0003WKH\u00034\u00035\u0003&RGH\u0003RQ\u0003WRS\u0003RI\u0003WKH\u0003SDJH\n\nLaboratory Investigation Report Patient Name : Mrs. Abhirupa Sen Age/Gender : 34 Y 0 M 0 D /F Max ID/Mobile : ML01514672/9879765568 Lab ID : 1887102100063 Ref Doctor : Dr.Jayshree Sundar Passport No. : Centre : 2132 - Azmat Diagnostics OP/IP No : / Collection Date/Time : 24/Oct/2021 12:27PM Receiving Date : 24/Oct/2021 Reporting Date : 24/Oct/2021 Clinical Biochemistry Diabetes Screening Profile 6,1\u00031R %\u0015E\u0014\u0013\u0018\u001b\u0018\u0019\u0017\u000f\u0003\u00037HVW\u00033HUIRUPHG\u0003DW\u0003",
        "start_char": 1803,
        "end_char": 3702,
        "token_count": 250,
        "metadata": {
          "page_count": 3,
          "pages_with_text": 3,
          "pages_processed": 3,
          "file_size_bytes": 357601,
          "storage_location": "/Users/pranesh/Devloper/Cloud Product/Doc/data/uploads/7294dc7f09524164b02649af30c6ef89_Diabetes Screening Profile - 44863.pdf",
          "storage_backend": "local",
          "original_char_count": 4049,
          "cleaned_char_count": 4013,
          "paragraph_count": 6,
          "start_token_index": 210,
          "end_token_index": 459
        }
      },
      {
        "chunk_id": "939bd8e43b7181895ccc3d0b90d449aacbfeb5a26a8565dc8b6d7ffdb6f80f5a",
        "document_id": "0aeaa6091659af4418b724141a8e520407c41f76fda7a6f6304674701cb08ba4",
        "chunk_index": 2,
        "text": ": 1887102100063 Ref Doctor : Dr.Jayshree Sundar Passport No. : Centre : 2132 - Azmat Diagnostics OP/IP No : / Collection Date/Time : 24/Oct/2021 12:27PM Receiving Date : 24/Oct/2021 Reporting Date : 24/Oct/2021 Clinical Biochemistry Diabetes Screening Profile 6,1\u00031R %\u0015E\u0014\u0013\u0018\u001b\u0018\u0019\u0017\u000f\u0003\u00037HVW\u00033HUIRUPHG\u0003DW\u0003\n\n\u0014\u0013\u0003\u0010\u00030D[\u0003+RVSLWDO\u0003\u0010\u00036DNHW\u00030\u00036\u00036\u0003+\u000f\u00033UHVV\u0003(QFODYH\u00035RDG\u000f\u00030DQGLU\u00030DUJ\u000f\u00036DNHW\u000f\u00031HZ\u0003'HOKL\u000f\u0003'HOKL\u0003\u0014\u0014\u0013\u0013\u0014\u001a %RRNLQJ\u0003&HQWUH\u0003 \u0015\u0014\u0016\u0015\u0003\u0010\u0003$]PDW\u0003'LDJQRVWLFV\u000f\u0003'\u0010\u0014\u0018\u0003)RXUWK\u0003)ORRU\u000f\u0003+D]L\u0003&RORQ\\\u000f\u0003-DPLD\u00031DJDU\u000f\u00032NKOD\u0003\u000f\u00031HZ\u0003'HOKL\u0010\u0015\u0018\u000f\u0003 \u001b\u001a\u0016\u0019\u0013\u0019\u0014\u001a\u0016 7KH\u0003DXWKHQWLFLW\\\u0003RI\u0003WKH\u0003UHSRUW\u0003FDQ\u0003EH\u0003YHULILHG\u0003E\\\u0003VFDQQLQJ\u0003WKH\u00034\u00035\u0003&RGH\u0003RQ\u0003WRS\u0003RI\u0003WKH\u0003SDJH",
        "start_char": 3404,
        "end_char": 4013,
        "token_count": 45,
        "metadata": {
          "page_count": 3,
          "pages_with_text": 3,
          "pages_processed": 3,
          "file_size_bytes": 357601,
          "storage_location": "/Users/pranesh/Devloper/Cloud Product/Doc/data/uploads/7294dc7f09524164b02649af30c6ef89_Diabetes Screening Profile - 44863.pdf",
          "storage_backend": "local",
          "original_char_count": 4049,
          "cleaned_char_count": 4013,
          "paragraph_count": 6,
          "start_token_index": 420,
          "end_token_index": 464
        }
      }
    ],
    "metadata": {
      "page_count": 3,
      "pages_with_text": 3,
      "pages_processed": 3,
      "file_size_bytes": 357601,
      "storage_location": "/Users/pranesh/Devloper/Cloud Product/Doc/data/uploads/7294dc7f09524164b02649af30c6ef89_Diabetes Screening Profile - 44863.pdf",
      "storage_backend": "local",
      "original_char_count": 4049,
      "cleaned_char_count": 4013,
      "paragraph_count": 6,
      "chunk_count": 3,
      "chunk_size": 250,
      "chunk_overlap": 40
    }
  },
  "analysis": {
    "document_id": "0aeaa6091659af4418b724141a8e520407c41f76fda7a6f6304674701cb08ba4",
    "summary": "Glucose 100 - 125 P.Glucose after 2 hrs 100 - 139 Impaired Glucose Tolerance: Fasting P.Glucose 74 - 99 P.Glucose after 2 hrs 140 - 199 Diabetes: Fasting P.Glucose \u0095\u0003\u0014\u0015\u0019 P.Glucose after 2 hrs \u0095\u0003\u0015\u0013\u0013 Diagnosis of Diabetes mellitus (DM), impaired glucose tolerance (IGT), impaired fasting glucose (IFG) on first occasion should be confirmed on another day. : Centre : 2132 - Azmat Diagnostics OP/IP No : / Collection Date/Time : 24/Oct/2021 12:27PM Receiving Date : 24/Oct/2021 Reporting Date : 24/Oct/2021 Clinical Biochemistry Diabetes Screening Profile 6,1\u00031R %\u0015E\u0014\u0013\u0018\u001b\u0018\u0019\u0017\u000f\u0003\u00037HVW\u00033HUIRUPHG\u0003DW\u0003 \u0014\u0013\u0003\u0010\u00030D[\u0003+RVSLWDO\u0003\u0010\u00036DNHW\u00030\u00036\u00036\u0003+\u000f\u00033UHVV\u0003(QFODYH\u00035RDG\u000f\u00030DQGLU\u00030DUJ\u000f\u00036DNHW\u000f\u00031HZ\u0003'HOKL\u000f\u0003'HOKL\u0003\u0014\u0014\u0013\u0013\u0014\u001a %RRNLQJ\u0003&HQWUH\u0003 \u0015\u0014\u0016\u0015\u0003\u0010\u0003$]PDW\u0003'LDJQRVWLFV\u000f\u0003'\u0010\u0014\u0018\u0003)RXUWK\u0003)ORRU\u000f\u0003+D]L\u0003&RORQ\\\u000f\u0003-DPLD\u00031DJDU\u000f\u00032NKOD\u0003\u000f\u00031HZ\u0003'HOKL\u0010\u0015\u0018\u000f\u0003 \u001b\u001a\u0016\u0019\u0013\u0019\u0014\u001a\u0016 7KH\u0003DXWKHQWLFLW\\\u0003RI\u0003WKH\u0003UHSRUW\u0003FDQ\u0003EH\u0003YHULILHG\u0003E\\\u0003VFDQQLQJ\u0003WKH\u00034\u00035\u0003&RGH\u0003RQ\u0003WRS\u0003RI\u0003WKH\u0003SDJH Laboratory Investigation Report Patient Name : Mrs. : Centre : 2132 - Azmat Diagnostics OP/IP No : / Collection Date/Time : 24/Oct/2021 12:27PM Receiving Date : 24/Oct/2021 Reporting Date : 24/Oct/2021 Clinical Biochemistry Diabetes Screening Profile 6,1\u00031R %\u0015E\u0014\u0013\u0018\u001b\u0018\u0019\u0017\u000f\u0003\u00037HVW\u00033HUIRUPHG\u0003DW\u0003 \u0014\u0013\u0003\u0010\u00030D[\u0003+RVSLWDO\u0003\u0010\u00036DNHW\u00030\u00036\u00036\u0003+\u000f\u00033UHVV\u0003(QFODYH\u00035RDG\u000f\u00030DQGLU\u00030DUJ\u000f\u00036DNHW\u000f\u00031HZ\u0003'HOKL\u000f\u0003'HOKL\u0003\u0014\u0014\u0013\u0013\u0014\u001a %RRNLQJ\u0003&HQWUH\u0003 \u0015\u0014\u0016\u0015\u0003\u0010\u0003$]PDW\u0003'LDJQRVWLFV\u000f\u0003'\u0010\u0014\u0018\u0003)RXUWK\u0003)ORRU\u000f\u0003+D]L\u0003&RORQ\\\u000f\u0003-DPLD\u00031DJDU\u000f\u00032NKOD\u0003\u000f\u00031HZ\u0003'HOKL\u0010\u0015\u0018\u000f\u0003 \u001b\u001a\u0016\u0019\u0013\u0019\u0014\u001a\u0016 7KH\u0003DXWKHQWLFLW\\\u0003RI\u0003WKH\u0003UHSRUW\u0003FDQ\u0003EH\u0003YHULILHG\u0003E\\\u0003VFDQQLQJ\u0003WKH\u00034\u00035\u0003&RGH\u0003RQ\u0003WRS\u0003RI\u0003WKH\u0003SDJH",
    "classification": {
      "label": "sales",
      "score": 0.12835949659347534,
      "metadata": {
        "candidate_labels": [
          "finance",
          "legal",
          "human resources",
          "engineering",
          "sales",
          "operations",
          "research",
          "compliance"
        ]
      }
    },
    "entities": [
      {
        "text": "Glucose Tolerance",
        "label": "PERSON",
        "start_char": 0,
        "end_char": 17,
        "score": null,
        "metadata": {}
      },
      {
        "text": "Hexokinase Glucose",
        "label": "PERSON",
        "start_char": 54,
        "end_char": 72,
        "score": null,
        "metadata": {}
      },
      {
        "text": "Blood Glucose",
        "label": "PERSON",
        "start_char": 100,
        "end_char": 113,
        "score": null,
        "metadata": {}
      },
      {
        "text": "Comment Impaired",
        "label": "PERSON",
        "start_char": 144,
        "end_char": 160,
        "score": null,
        "metadata": {}
      },
      {
        "text": "Fasting Glucose",
        "label": "PERSON",
        "start_char": 161,
        "end_char": 176,
        "score": null,
        "metadata": {}
      },
      {
        "text": "Impaired Glucose",
        "label": "PERSON",
        "start_char": 239,
        "end_char": 255,
        "score": null,
        "metadata": {}
      },
      {
        "text": "Laboratory Investigation",
        "label": "PERSON",
        "start_char": 747,
        "end_char": 771,
        "score": null,
        "metadata": {}
      },
      {
        "text": "Report Patient",
        "label": "PERSON",
        "start_char": 772,
        "end_char": 786,
        "score": null,
        "metadata": {}
      },
      {
        "text": "Abhirupa Sen",
        "label": "PERSON",
        "start_char": 799,
        "end_char": 811,
        "score": null,
        "metadata": {}
      },
      {
        "text": "Ref Doctor",
        "label": "PERSON",
        "start_char": 902,
        "end_char": 912,
        "score": null,
        "metadata": {}
      },
      {
        "text": "Jayshree Sundar",
        "label": "PERSON",
        "start_char": 918,
        "end_char": 933,
        "score": null,
        "metadata": {}
      },
      {
        "text": "Passport No",
        "label": "PERSON",
        "start_char": 934,
        "end_char": 945,
        "score": null,
        "metadata": {}
      },
      {
        "text": "Azmat Diagnostics",
        "label": "PERSON",
        "start_char": 965,
        "end_char": 982,
        "score": null,
        "metadata": {}
      },
      {
        "text": "Collection Date",
        "label": "PERSON",
        "start_char": 996,
        "end_char": 1011,
        "score": null,
        "metadata": {}
      },
      {
        "text": "Receiving Date",
        "label": "PERSON",
        "start_char": 1039,
        "end_char": 1053,
        "score": null,
        "metadata": {}
      },
      {
        "text": "Reporting Date",
        "label": "PERSON",
        "start_char": 1068,
        "end_char": 1082,
        "score": null,
        "metadata": {}
      },
      {
        "text": "Clinical Biochemistry",
        "label": "PERSON",
        "start_char": 1097,
        "end_char": 1118,
        "score": null,
        "metadata": {}
      },
      {
        "text": "Diabetes Screening",
        "label": "PERSON",
        "start_char": 1119,
        "end_char": 1137,
        "score": null,
        "metadata": {}
      },
      {
        "text": "Profile Test",
        "label": "PERSON",
        "start_char": 1138,
        "end_char": 1150,
        "score": null,
        "metadata": {}
      },
      {
        "text": "Name Result",
        "label": "PERSON",
        "start_char": 1151,
        "end_char": 1162,
        "score": null,
        "metadata": {}
      },
      {
        "text": "Unit Bio",
        "label": "PERSON",
        "start_char": 1163,
        "end_char": 1171,
        "score": null,
        "metadata": {}
      },
      {
        "text": "Ref Interval",
        "label": "PERSON",
        "start_char": 1172,
        "end_char": 1184,
        "score": null,
        "metadata": {}
      },
      {
        "text": "Glycosylated Haemoglobin",
        "label": "PERSON",
        "start_char": 1536,
        "end_char": 1560,
        "score": null,
        "metadata": {}
      },
      {
        "text": "Unit Bio",
        "label": "PERSON",
        "start_char": 1612,
        "end_char": 1620,
        "score": null,
        "metadata": {}
      },
      {
        "text": "Ref Interval",
        "label": "PERSON",
        "start_char": 1621,
        "end_char": 1633,
        "score": null,
        "metadata": {}
      },
      {
        "text": "Glycosylated Haemoglobin",
        "label": "PERSON",
        "start_char": 1634,
        "end_char": 1658,
        "score": null,
        "metadata": {}
      },
      {
        "text": "Glycosylated Haemoglobin",
        "label": "PERSON",
        "start_char": 1679,
        "end_char": 1703,
        "score": null,
        "metadata": {}
      },
      {
        "text": "Average Glucose",
        "label": "PERSON",
        "start_char": 1739,
        "end_char": 1754,
        "score": null,
        "metadata": {}
      },
      {
        "text": "Value For",
        "label": "PERSON",
        "start_char": 1755,
        "end_char": 1764,
        "score": null,
        "metadata": {}
      },
      {
        "text": "Average Glucose",
        "label": "PERSON",
        "start_char": 1795,
        "end_char": 1810,
        "score": null,
        "metadata": {}
      },
      {
        "text": "Value For",
        "label": "PERSON",
        "start_char": 1811,
        "end_char": 1820,
        "score": null,
        "metadata": {}
      },
      {
        "text": "Interpretation The",
        "label": "PERSON",
        "start_char": 1856,
        "end_char": 1874,
        "score": null,
        "metadata": {}
      },
      {
        "text": "American Diabetes",
        "label": "PERSON",
        "start_char": 1917,
        "end_char": 1934,
        "score": null,
        "metadata": {}
      },
      {
        "text": "Suggested Diagnosis",
        "label": "PERSON",
        "start_char": 2047,
        "end_char": 2066,
        "score": null,
        "metadata": {}
      },
      {
        "text": "Increased Glycated",
        "label": "PERSON",
        "start_char": 2389,
        "end_char": 2407,
        "score": null,
        "metadata": {}
      },
      {
        "text": "End Of",
        "label": "PERSON",
        "start_char": 2497,
        "end_char": 2503,
        "score": null,
        "metadata": {}
      },
      {
        "text": "Laboratory Investigation",
        "label": "PERSON",
        "start_char": 2515,
        "end_char": 2539,
        "score": null,
        "metadata": {}
      },
      {
        "text": "Report Patient",
        "label": "PERSON",
        "start_char": 2540,
        "end_char": 2554,
        "score": null,
        "metadata": {}
      },
      {
        "text": "Abhirupa Sen",
        "label": "PERSON",
        "start_char": 2567,
        "end_char": 2579,
        "score": null,
        "metadata": {}
      },
      {
        "text": "Ref Doctor",
        "label": "PERSON",
        "start_char": 2670,
        "end_char": 2680,
        "score": null,
        "metadata": {}
      },
      {
        "text": "Jayshree Sundar",
        "label": "PERSON",
        "start_char": 2686,
        "end_char": 2701,
        "score": null,
        "metadata": {}
      },
      {
        "text": "Passport No",
        "label": "PERSON",
        "start_char": 2702,
        "end_char": 2713,
        "score": null,
        "metadata": {}
      },
      {
        "text": "Azmat Diagnostics",
        "label": "PERSON",
        "start_char": 2733,
        "end_char": 2750,
        "score": null,
        "metadata": {}
      },
      {
        "text": "Collection Date",
        "label": "PERSON",
        "start_char": 2764,
        "end_char": 2779,
        "score": null,
        "metadata": {}
      },
      {
        "text": "Receiving Date",
        "label": "PERSON",
        "start_char": 2807,
        "end_char": 2821,
        "score": null,
        "metadata": {}
      },
      {
        "text": "Reporting Date",
        "label": "PERSON",
        "start_char": 2836,
        "end_char": 2850,
        "score": null,
        "metadata": {}
      },
      {
        "text": "Clinical Biochemistry",
        "label": "PERSON",
        "start_char": 2865,
        "end_char": 2886,
        "score": null,
        "metadata": {}
      },
      {
        "text": "Diabetes Screening",
        "label": "PERSON",
        "start_char": 2887,
        "end_char": 2905,
        "score": null,
        "metadata": {}
      },
      {
        "text": "Laboratory Investigation",
        "label": "PERSON",
        "start_char": 3265,
        "end_char": 3289,
        "score": null,
        "metadata": {}
      },
      {
        "text": "Report Patient",
        "label": "PERSON",
        "start_char": 3290,
        "end_char": 3304,
        "score": null,
        "metadata": {}
      },
      {
        "text": "Abhirupa Sen",
        "label": "PERSON",
        "start_char": 3317,
        "end_char": 3329,
        "score": null,
        "metadata": {}
      },
      {
        "text": "Ref Doctor",
        "label": "PERSON",
        "start_char": 3420,
        "end_char": 3430,
        "score": null,
        "metadata": {}
      },
      {
        "text": "Jayshree Sundar",
        "label": "PERSON",
        "start_char": 3436,
        "end_char": 3451,
        "score": null,
        "metadata": {}
      },
      {
        "text": "Passport No",
        "label": "PERSON",
        "start_char": 3452,
        "end_char": 3463,
        "score": null,
        "metadata": {}
      },
      {
        "text": "Azmat Diagnostics",
        "label": "PERSON",
        "start_char": 3483,
        "end_char": 3500,
        "score": null,
        "metadata": {}
      },
      {
        "text": "Collection Date",
        "label": "PERSON",
        "start_char": 3514,
        "end_char": 3529,
        "score": null,
        "metadata": {}
      },
      {
        "text": "Receiving Date",
        "label": "PERSON",
        "start_char": 3557,
        "end_char": 3571,
        "score": null,
        "metadata": {}
      },
      {
        "text": "Reporting Date",
        "label": "PERSON",
        "start_char": 3586,
        "end_char": 3600,
        "score": null,
        "metadata": {}
      },
      {
        "text": "Clinical Biochemistry",
        "label": "PERSON",
        "start_char": 3615,
        "end_char": 3636,
        "score": null,
        "metadata": {}
      },
      {
        "text": "Diabetes Screening",
        "label": "PERSON",
        "start_char": 3637,
        "end_char": 3655,
        "score": null,
        "metadata": {}
      }
    ],
    "keywords": [
      {
        "keyword": "diabetes",
        "score": 0.4696,
        "metadata": {}
      },
      {
        "keyword": "hyperglycemia",
        "score": 0.4598,
        "metadata": {}
      },
      {
        "keyword": "glucose",
        "score": 0.456,
        "metadata": {}
      },
      {
        "keyword": "glycaemia",
        "score": 0.4389,
        "metadata": {}
      },
      {
        "keyword": "diagnostics",
        "score": 0.2436,
        "metadata": {}
      },
      {
        "keyword": "cardiovascular",
        "score": 0.2415,
        "metadata": {}
      },
      {
        "keyword": "abhirupa",
        "score": 0.2378,
        "metadata": {}
      },
      {
        "keyword": "75gm",
        "score": 0.2045,
        "metadata": {}
      },
      {
        "keyword": "fasting",
        "score": 0.1925,
        "metadata": {}
      },
      {
        "keyword": "hba1c",
        "score": 0.1588,
        "metadata": {}
      }
    ],
    "metadata": {
      "generated_at": "2026-03-23T20:40:55.295130+00:00"
    }
  },
  "metadata": {
    "stored_object_id": "7294dc7f09524164b02649af30c6ef89",
    "stored_location": "/Users/pranesh/Devloper/Cloud Product/Doc/data/uploads/7294dc7f09524164b02649af30c6ef89_Diabetes Screening Profile - 44863.pdf"
  }
}